.gitignore
pyproject.toml
.github/workflows/python-publish.yml
src/framepump/__init__.py
src/framepump/_version.py
src/framepump/framepump.py
src/framepump/video_writing.py
src/framepump.egg-info/PKG-INFO
src/framepump.egg-info/SOURCES.txt
src/framepump.egg-info/dependency_links.txt
src/framepump.egg-info/requires.txt
src/framepump.egg-info/top_level.txt