Metadata-Version: 2.4
Name: framepump
Version: 0.1.4
Summary: Video processing utilities
Author-email: István Sárándi <istvan.sarandi@uni-tuebingen.de>
License-Expression: MIT
Project-URL: Homepage, https://github.com/isarandi/framepump
Project-URL: Repository, https://github.com/isarandi/framepump
Project-URL: Issues, https://github.com/isarandi/framepump/issues
Project-URL: Author, https://istvansarandi.com
Classifier: Development Status :: 4 - Beta
Classifier: Intended Audience :: Developers
Classifier: Topic :: Software Development :: Libraries
Classifier: Programming Language :: Python
Classifier: Programming Language :: Python :: 3
Classifier: Operating System :: POSIX :: Linux
Requires-Python: >=3.8
Requires-Dist: numpy
Requires-Dist: imageio
Requires-Dist: imageio-ffmpeg
Requires-Dist: ffmpeg-python
Requires-Dist: simplepyutils
